ftllm/__init__.py
ftllm/chat.py
ftllm/cli.py
ftllm/download.py
ftllm/export.py
ftllm/hf_model.py
ftllm/libfastllm_tools-cpu.so
ftllm/libfastllm_tools.so
ftllm/libnuma.so.1
ftllm/llm.py
ftllm/server.py
ftllm/torch2flm.py
ftllm/ui.py
ftllm/util.py
ftllm/web_demo.py
ftllm/webui.py
ftllm/openai_server/fastllm_completion.py
ftllm/openai_server/fastllm_embed.py
ftllm/openai_server/fastllm_model.py
ftllm/openai_server/fastllm_reranker.py
ftllm/openai_server/protocal/openai_protocol.py
ftllm_rocm-0.1.5.1.dist-info/METADATA
ftllm_rocm-0.1.5.1.dist-info/WHEEL
ftllm_rocm-0.1.5.1.dist-info/entry_points.txt
ftllm_rocm-0.1.5.1.dist-info/top_level.txt
ftllm_rocm-0.1.5.1.dist-info/RECORD
