Metadata-Version: 2.1
Name: ftllm-rocm
Version: 0.1.5.1
Summary: Fastllm
Home-page: https://github.com/ztxz16/fastllm
Author: huangyuyang
Author-email: ztxz16@foxmail.com
License: UNKNOWN
Platform: UNKNOWN
Requires-Dist: aria2
Requires-Dist: fastapi
Requires-Dist: jinja2 (>=3.1.0)
Requires-Dist: openai
Requires-Dist: pydantic
Requires-Dist: pyreadline3
Requires-Dist: shortuuid
Requires-Dist: streamlit-chat
Requires-Dist: transformers
Requires-Dist: uvicorn
Provides-Extra: all
Requires-Dist: aria2 ; extra == 'all'
Requires-Dist: fastapi ; extra == 'all'
Requires-Dist: openai ; extra == 'all'
Requires-Dist: pydantic ; extra == 'all'
Requires-Dist: shortuuid ; extra == 'all'
Requires-Dist: streamlit-chat ; extra == 'all'
Requires-Dist: uvicorn ; extra == 'all'
Provides-Extra: server
Requires-Dist: fastapi ; extra == 'server'
Requires-Dist: openai ; extra == 'server'
Requires-Dist: pydantic ; extra == 'server'
Requires-Dist: shortuuid ; extra == 'server'
Requires-Dist: uvicorn ; extra == 'server'
Provides-Extra: webui
Requires-Dist: streamlit-chat ; extra == 'webui'
